ossi_tool3/__init__.py
ossi_tool3/__main__.py
ossi_tool3/ossit.py
ossi_tool3-0.4.0.1.dist-info/LICENSE
ossi_tool3-0.4.0.1.dist-info/METADATA
ossi_tool3-0.4.0.1.dist-info/WHEEL
ossi_tool3-0.4.0.1.dist-info/entry_points.txt
ossi_tool3-0.4.0.1.dist-info/top_level.txt
ossi_tool3-0.4.0.1.dist-info/RECORD
