Metadata-Version: 2.1
Name: ossi-tool3
Version: 0.4.0.1
Summary: Avaya SAT (Communication Manager Site Administration Tool) python emulator, to generate CSV file from command output
Home-page: https://github.com/deesnow/ossi_tool3
Author: Janos Tarjanyi
Author-email: janos.tarajnyi@gmail.com
License: ISC
Platform: UNKNOWN
Classifier: Development Status :: 3 - Alpha
Classifier: Environment :: Console
Classifier: Programming Language :: Python :: 3
Classifier: Intended Audience :: Telecommunications Industry
Classifier: Topic :: Communications :: Telephony
Classifier: License :: OSI Approved :: ISC License (ISCL)
Requires-Dist: pexpect
